dinobytes/__init__.py
dinobytes/dinobytes.py
dinobytes-0.4.0.dist-info/LICENSE
dinobytes-0.4.0.dist-info/METADATA
dinobytes-0.4.0.dist-info/WHEEL
dinobytes-0.4.0.dist-info/RECORD
