Metadata-Version: 2.1
Name: dinobytes
Version: 0.4.0
Summary: 
Author: Kyle Dougan
Author-email: kdougan@gmail.com
Requires-Python: >=3.11,<4.0
Classifier: Programming Language :: Python :: 3
Classifier: Programming Language :: Python :: 3.11
Classifier: Programming Language :: Python :: 3.12
Requires-Dist: ormsgpack (>=1.4.2,<2.0.0)
